mbsim/core/__init__.py
mbsim/core/client.py
mbsim/core/server.py
mbsim/core/tasks.py
mbsim_core-1.0.2.post0.dist-info/licenses/LICENSE.txt
mbsim_core-1.0.2.post0.dist-info/METADATA
mbsim_core-1.0.2.post0.dist-info/WHEEL
mbsim_core-1.0.2.post0.dist-info/top_level.txt
mbsim_core-1.0.2.post0.dist-info/RECORD
