Metadata-Version: 2.4
Name: mbsim_core
Version: 1.0.2.post0
Summary: Core server for mbsim to start server
Home-page: https://gitlab.com/nee2c/mbsim-core
Author: nee2c
Author-email: nico2c3c@gmail.com
License: MIT
Project-URL: Documentation, http://mbsim-core.rtfd.io/
Platform: Linux
Classifier: Development Status :: 4 - Beta
Classifier: License :: OSI Approved :: MIT License
Classifier: Programming Language :: Python
Classifier: Programming Language :: Python :: 3
Classifier: Programming Language :: Python :: 3 :: Only
Classifier: Programming Language :: Python :: Implementation :: CPython
Requires-Python: >=3.9
License-File: LICENSE.txt
Requires-Dist: pymodbus<3.10.0; python_version >= "3.9"
Provides-Extra: dev
Requires-Dist: pre-commit; extra == "dev"
Requires-Dist: setuptools; extra == "dev"
Requires-Dist: tox; extra == "dev"
Provides-Extra: docs
Requires-Dist: sphinx; extra == "docs"
Requires-Dist: sphinx-rtd-theme; extra == "docs"
Provides-Extra: test
Requires-Dist: pytest; extra == "test"
Requires-Dist: pytest-asyncio; extra == "test"
Requires-Dist: pytest-cov; extra == "test"
Dynamic: license-file
